gempyp/__init__.py
gempyp/cli.py
gempyp/config/DefaultSettings.py
gempyp/config/GitLinkXML.py
gempyp/config/Result.html
gempyp/config/__init__.py
gempyp/config/baseConfig.py
gempyp/config/customParser.py
gempyp/config/gempyp.conf
gempyp/config/suite_conf.json
gempyp/config/xmlConfig.py
gempyp/data_compare/__init__.py
gempyp/data_compare/common/__init__.py
gempyp/data_compare/common/common_functions.py
gempyp/data_compare/compare.py
gempyp/data_compare/config/dvm.json
gempyp/data_compare/configurator/__init__.py
gempyp/data_compare/configurator/configurator.py
gempyp/data_compare/configurator/validator.py
gempyp/data_compare/core/Compare.py
gempyp/data_compare/core/__init__.py
gempyp/data_compare/core/comparator.py
gempyp/data_compare/core/python_obj_comparator.py
gempyp/data_compare/data/__init__.py
gempyp/data_compare/data/data.py
gempyp/data_compare/data/database.py
gempyp/data_compare/data/db_mysql.py
gempyp/data_compare/data/db_oracle.py
gempyp/data_compare/data/db_postgre.py
gempyp/data_compare/data/db_sqlite.py
gempyp/data_compare/data/file_processor.py
gempyp/data_compare/data_comp.py
gempyp/data_compare/report/__init__.py
gempyp/data_compare/tools/__init__.py
gempyp/data_uploader.py
gempyp/dv/__init__.py
gempyp/dv/dfOperations.py
gempyp/dv/dvCompare.py
gempyp/dv/dvDatabases.py
gempyp/dv/dvDataframe.py
gempyp/dv/dvObj.py
gempyp/dv/dvReporting.py
gempyp/dv/dvRunner.py
gempyp/engine/__init__.py
gempyp/engine/baseTemplate.py
gempyp/engine/dataUpload.py
gempyp/engine/engine.py
gempyp/engine/executors/__init__.py
gempyp/engine/executors/baseExecutor.py
gempyp/engine/gempypHelper.py
gempyp/engine/runner.py
gempyp/engine/simpleTestcase.py
gempyp/engine/testData.py
gempyp/final_report.html
gempyp/gemPyp.py
gempyp/jira/__init__.py
gempyp/jira/azureIntegration.py
gempyp/jira/jiraIntegration.py
gempyp/jira/jiraIntegrationCopy.py
gempyp/libs/__init__.py
gempyp/libs/common.py
gempyp/libs/enums/run_types.py
gempyp/libs/enums/status.py
gempyp/libs/exceptions/__init__.py
gempyp-2.3.0.dist-info/LICENSE
gempyp-2.3.0.dist-info/METADATA
gempyp-2.3.0.dist-info/WHEEL
gempyp-2.3.0.dist-info/entry_points.txt
gempyp-2.3.0.dist-info/RECORD
