Metadata-Version: 2.3
Name: gempyp
Version: 2.3.0
Summary: An ecosystem of libraries useful for software development
License: MIT
Author: Gemini Solutions-QA
Requires-Python: >=3.12.0,<4.0.0
Classifier: License :: OSI Approved :: MIT License
Classifier: Programming Language :: Python :: 3
Classifier: Programming Language :: Python :: 3.12
Classifier: Programming Language :: Python :: 3.13
Requires-Dist: XlsxWriter (>=3.0.3,<4.0.0)
Requires-Dist: certifi (>=2025.7.14,<2026.0.0)
Requires-Dist: cffi (>=1.15.0,<2.0.0)
Requires-Dist: charset-normalizer (>=2.0.12,<3.0.0)
Requires-Dist: coloredlogs (>=15.0.1,<16.0.0)
Requires-Dist: cryptography (>=44.0.1,<45.0.0)
Requires-Dist: humanfriendly (>=10.0,<11.0)
Requires-Dist: idna (>=3.7,<4.0)
Requires-Dist: lxml (>=6.0.0,<7.0.0)
Requires-Dist: mysql-connector-python (>=9.1.0,<10.0.0)
Requires-Dist: ntlm-auth (>=1.5.0,<2.0.0)
Requires-Dist: numpy (>=2.3.1,<3.0.0)
Requires-Dist: pandas (>=2.3.1,<3.0.0)
Requires-Dist: pg8000 (>=1.26.0,<2.0.0)
Requires-Dist: pycparser (>=2.21,<3.0)
Requires-Dist: pymongo (>=4.6.3,<5.0.0)
Requires-Dist: pyreadline (>=2.1,<3.0)
Requires-Dist: pyreadline3 (>=3.4.1,<4.0.0)
Requires-Dist: pytest (>=7.2.0,<8.0.0)
Requires-Dist: python-dateutil (>=2.8.2,<3.0.0)
Requires-Dist: pytz (>=2022.2.1,<2023.0.0)
Requires-Dist: requests (>=2.32.4,<3.0.0)
Requires-Dist: requests-ntlm (>=1.1.0,<2.0.0)
Requires-Dist: six (>=1.16.0,<2.0.0)
Requires-Dist: snowflake-connector-python (>=3.16.0,<4.0.0)
Requires-Dist: urllib3 (>=2.5.0,<3.0.0)
Project-URL: Documentation, https://blustone.gemecosystem.com/category/documentation/documentation-gempyp/
Project-URL: Homepage, https://gempyp.gemecosystem.com
Project-URL: Repository, https://gitea.geminisolutions.com/Gemini-Solutions/gempyp/src/branch/beta_release/
